{"features":[{"geometry":[[[4160,1466],[2976,-64],[4160,-64],[4160,1466]]],"type":3,"tags":{"code":"45098","nom":"Cléry-Saint-André","population":3596,"density":196},"id":"45098"},{"geometry":[[[1750,-64],[1083,237],[725,-64],[1750,-64]]],"type":3,"tags":{"code":"45203","nom":"Meung-sur-Loire","population":6670,"density":330},"id":"45203"},{"geometry":[[[1144,-64],[-64,1582],[-64,-64],[1144,-64]]],"type":3,"tags":{"code":"45024","nom":"Baule","population":1985,"density":166},"id":"45024"},{"geometry":[[[-64,1768],[634,1321],[3508,3362],[3597,4160],[-64,4160],[-64,1768]]],"type":3,"tags":{"code":"45179","nom":"Lailly-en-Val","population":3101,"density":67},"id":"45179"},{"geometry":[[[634,1321],[1083,237],[1760,-64],[3041,-64],[4160,1441],[4160,2527],[3175,3405],[634,1321]]],"type":3,"tags":{"code":"45130","nom":"Dry","population":1408,"density":61},"id":"45130"},{"geometry":[[[3597,4160],[3508,3362],[4160,2659],[4160,4160],[3597,4160]]],"type":3,"tags":{"code":"45175","nom":"Jouy-le-Potier","population":1643,"density":32},"id":"45175"}]}