{"features":[{"geometry":[[[-64,3917],[459,4160],[-64,4160],[-64,3917]]],"type":3,"tags":{"code":"46031","nom":"Blars","population":137,"density":5},"id":"46031"},{"geometry":[[[2602,-64],[1740,1656],[1862,3166],[956,4160],[409,4160],[-64,3933],[-64,-64],[2602,-64]]],"type":3,"tags":{"code":"46094","nom":"Espédaillac","population":290,"density":8},"id":"46094"},{"geometry":[[[1616,3256],[3988,2874],[3644,3632],[3967,4160],[2560,4160],[2601,3627],[1616,3256]]],"type":3,"tags":{"code":"46039","nom":"Brengues","population":195,"density":9},"id":"46039"},{"geometry":[[[3930,3021],[4160,3066],[4160,4160],[3977,4160],[3644,3632],[3930,3021]]],"type":3,"tags":{"code":"46093","nom":"Espagnac-Sainte-Eulalie","population":97,"density":10},"id":"46093"},{"geometry":[[[4160,2881],[2835,2963],[1740,1656],[2420,944],[4160,1834],[4160,2881]]],"type":3,"tags":{"code":"46131","nom":"Grèzes","population":155,"density":14},"id":"46131"},{"geometry":[[[4160,-64],[4160,1951],[4010,1963],[2420,944],[2331,-64],[4160,-64]]],"type":3,"tags":{"code":"46176","nom":"Livernon","population":722,"density":28},"id":"46176"},{"geometry":[[[1212,4160],[1393,3325],[2601,3627],[2554,4160],[1212,4160]]],"type":3,"tags":{"code":"46294","nom":"Saint-Sulpice","population":127,"density":10},"id":"46294"}]}