{"features":[{"geometry":[[[-64,2279],[1365,2752],[-64,3124],[-64,2279]]],"type":3,"tags":{"code":"51364","nom":"Méry-Prémecy","population":68,"density":13},"id":"51364"},{"geometry":[[[2032,4160],[3467,3519],[2960,4160],[2032,4160]]],"type":3,"tags":{"code":"51310","nom":"Jouy-lès-Reims","population":204,"density":109},"id":"51310"},{"geometry":[[[690,2139],[745,694],[1624,-29],[2663,44],[3252,1174],[690,2139]]],"type":3,"tags":{"code":"51282","nom":"Gueux","population":1907,"density":215},"id":"51282"},{"geometry":[[[4160,510],[3899,536],[3576,-64],[4160,-64],[4160,510]]],"type":3,"tags":{"code":"51118","nom":"Champigny","population":1647,"density":375},"id":"51118"},{"geometry":[[[-64,3606],[158,3575],[-64,4106],[-64,3606]]],"type":3,"tags":{"code":"51020","nom":"Aubilly","population":50,"density":16},"id":"51020"},{"geometry":[[[1116,3194],[1708,2590],[3247,2719],[1116,3194]]],"type":3,"tags":{"code":"51177","nom":"Coulommes-la-Montagne","population":209,"density":76},"id":"51177"},{"geometry":[[[-64,1256],[545,1063],[-64,2043],[-64,1256]]],"type":3,"tags":{"code":"51267","nom":"Germigny","population":188,"density":79},"id":"51267"},{"geometry":[[[545,1063],[758,2065],[-64,2093],[-64,2071],[545,1063]]],"type":3,"tags":{"code":"51305","nom":"Janvry","population":155,"density":79},"id":"51305"},{"geometry":[[[3466,3753],[4160,3185],[4160,3950],[3466,3753]]],"type":3,"tags":{"code":"51365","nom":"Mesneux","population":966,"density":231},"id":"51365"},{"geometry":[[[2188,-64],[1985,194],[269,-64],[2188,-64]]],"type":3,"tags":{"code":"51391","nom":"Muizon","population":2081,"density":293},"id":"51391"},{"geometry":[[[3135,2613],[3608,1461],[4160,1533],[4160,2829],[3728,3159],[3135,2613]]],"type":3,"tags":{"code":"51418","nom":"Ormes","population":576,"density":92},"id":"51418"},{"geometry":[[[2025,4160],[1549,3601],[3728,3159],[2031,4160],[2025,4160]]],"type":3,"tags":{"code":"51422","nom":"Pargny-lès-Reims","population":497,"density":137},"id":"51422"},{"geometry":[[[-64,8],[990,528],[-64,1060],[-64,8]]],"type":3,"tags":{"code":"51468","nom":"Rosnay","population":423,"density":76},"id":"51468"},{"geometry":[[[54,3493],[1618,3370],[1720,4160],[81,4160],[54,3493]]],"type":3,"tags":{"code":"51479","nom":"Saint-Euphraise-et-Clairizet","population":244,"density":50},"id":"51479"},{"geometry":[[[3892,-64],[4160,202],[4160,1317],[3236,1743],[2650,-64],[3892,-64]]],"type":3,"tags":{"code":"51569","nom":"Thillois","population":514,"density":81},"id":"51569"},{"geometry":[[[3466,3753],[4160,4138],[4160,4160],[2986,4160],[3466,3753]]],"type":3,"tags":{"code":"51622","nom":"Ville-Dommange","population":407,"density":119},"id":"51622"},{"geometry":[[[1061,2120],[2986,1346],[3424,2132],[1390,2795],[1061,2120]]],"type":3,"tags":{"code":"51657","nom":"Vrigny","population":234,"density":52},"id":"51657"}]}