{"features":[{"geometry":[[[2262,-64],[2249,-26],[1235,295],[634,-64],[2262,-64]]],"type":3,"tags":{"code":"40034","nom":"Bélus","population":615,"density":52},"id":"40034"},{"geometry":[[[1598,4160],[950,2859],[3008,2871],[2642,4160],[1598,4160]]],"type":3,"tags":{"code":"40206","nom":"Oeyregave","population":321,"density":41},"id":"40206"},{"geometry":[[[2407,-64],[2249,-26],[2262,-64],[2407,-64]]],"type":3,"tags":{"code":"40059","nom":"Cagnotte","population":784,"density":53},"id":"40059"},{"geometry":[[[2432,2582],[2003,2522],[2756,2315],[2939,-64],[3980,-64],[3904,377],[4160,600],[4160,2465],[2432,2582]]],"type":3,"tags":{"code":"40077","nom":"Cauneille","population":804,"density":53},"id":"40077"},{"geometry":[[[567,4160],[594,4151],[-64,3453],[-64,2648],[1322,2580],[950,2859],[1598,4160],[567,4160]]],"type":3,"tags":{"code":"40120","nom":"Hastingues","population":609,"density":42},"id":"40120"},{"geometry":[[[764,-64],[1235,295],[124,2445],[-64,2494],[-64,-64],[764,-64]]],"type":3,"tags":{"code":"40212","nom":"Orthevielle","population":1073,"density":77},"id":"40212"},{"geometry":[[[124,2445],[1235,295],[2339,-64],[2842,-64],[2674,2419],[124,2445]]],"type":3,"tags":{"code":"40224","nom":"Peyrehorade","population":3700,"density":228},"id":"40224"},{"geometry":[[[4160,576],[3881,265],[4160,-9],[4160,576]]],"type":3,"tags":{"code":"40233","nom":"Pouillon","population":3134,"density":63},"id":"40233"},{"geometry":[[[3202,4160],[2432,2582],[4160,2584],[4160,4160],[3202,4160]]],"type":3,"tags":{"code":"40306","nom":"Sorde-l'Abbaye","population":645,"density":40},"id":"40306"},{"geometry":[[[2676,4160],[2866,3690],[3088,4160],[2676,4160]]],"type":3,"tags":{"code":"64161","nom":"Came","population":1024,"density":30},"id":"64161"},{"geometry":[[[-64,3727],[267,4160],[-64,4160],[-64,3727]]],"type":3,"tags":{"code":"64502","nom":"Sames","population":709,"density":54},"id":"64502"}]}