{"features":[{"geometry":[[[2728,2176],[2845,459],[4160,630],[4160,1780],[4029,1998],[2728,2176]]],"type":3,"tags":{"code":"29005","nom":"Baye","population":1369,"density":188},"id":"29005"},{"geometry":[[[3613,149],[3614,-64],[4160,-64],[4160,221],[3613,149]]],"type":3,"tags":{"code":"29147","nom":"Mellac","population":3404,"density":129},"id":"29147"},{"geometry":[[[-64,4160],[-64,3678],[1941,3566],[3229,1865],[4160,2034],[4160,4160],[-64,4160]]],"type":3,"tags":{"code":"29150","nom":"Moëlan-sur-Mer","population":6749,"density":142},"id":"29150"},{"geometry":[[[4160,2287],[3880,2341],[4160,2005],[4160,2287]]],"type":3,"tags":{"code":"29233","nom":"Quimperlé","population":12469,"density":409},"id":"29233"},{"geometry":[[[2416,2994],[38,3608],[-64,3273],[-64,-64],[6,-64],[25,59],[703,555],[1743,-64],[3660,-64],[2845,459],[2416,2994]]],"type":3,"tags":{"code":"29236","nom":"Riec-sur-Bélon","population":4376,"density":80},"id":"29236"},{"geometry":[[[1743,-64],[703,555],[25,59],[6,-64],[1743,-64]]],"type":3,"tags":{"code":"29300","nom":"Trévoux","population":1652,"density":79},"id":"29300"}]}