{"features":[{"geometry":[[[3009,0],[2945,-64],[3060,-64],[3009,0]]],"type":3,"tags":{"code":"85049","nom":"Champagné-les-Marais","population":1824,"density":37},"id":"85049"},{"geometry":[[[3820,-64],[3854,-15],[3380,-11],[3405,-64],[3820,-64]]],"type":3,"tags":{"code":"85267","nom":"Sainte-Radégonde-des-Noyers","population":990,"density":32},"id":"85267"},{"geometry":[[[2705,-64],[2379,8],[2364,-64],[2705,-64]]],"type":3,"tags":{"code":"85297","nom":"Triaize","population":1071,"density":19},"id":"85297"},{"geometry":[[[3664,4160],[3531,3731],[3986,4160],[3664,4160]]],"type":3,"tags":{"code":"17094","nom":"Châtelaillon-Plage","population":6653,"density":1009},"id":"17094"},{"geometry":[[[4156,3814],[4160,3816],[4160,4160],[3994,4160],[3812,3970],[4156,3814]]],"type":3,"tags":{"code":"17413","nom":"Saint-Vivien","population":1436,"density":174},"id":"17413"},{"geometry":[[[2389,2118],[2432,1872],[2802,2038],[2715,2267],[2389,2118]]],"type":3,"tags":{"code":"17190","nom":"Houmeau","population":3000,"density":674},"id":"17190"},{"geometry":[[[3951,901],[3978,560],[4160,631],[4160,1131],[4147,1125],[4160,1110],[4160,934],[3951,901]]],"type":3,"tags":{"code":"17008","nom":"Andilly","population":2350,"density":82},"id":"17008"},{"geometry":[[[3531,3731],[3063,3503],[3438,3266],[3837,3683],[3531,3731]]],"type":3,"tags":{"code":"17010","nom":"Angoulins","population":4240,"density":530},"id":"17010"},{"geometry":[[[3291,3422],[3239,3200],[3014,3172],[3020,2974],[3502,2809],[3798,3042],[3291,3422]]],"type":3,"tags":{"code":"17028","nom":"Aytré","population":9746,"density":797},"id":"17028"},{"geometry":[[[498,2600],[-64,2232],[-64,2230],[34,1960],[711,2184],[629,2577],[498,2600]]],"type":3,"tags":{"code":"17051","nom":"Bois-Plage-en-Ré","population":2125,"density":174},"id":"17051"},{"geometry":[[[3436,934],[3226,106],[3304,-64],[3409,-64],[3618,76],[3764,-64],[4160,-64],[4160,631],[3978,560],[3842,964],[3436,934]]],"type":3,"tags":{"code":"17091","nom":"Charron","population":2021,"density":56},"id":"17091"},{"geometry":[[[4160,3054],[4013,3055],[4068,2822],[4160,2786],[4160,3054]]],"type":3,"tags":{"code":"17109","nom":"Clavette","population":1406,"density":223},"id":"17109"},{"geometry":[[[-64,1894],[73,1954],[-64,2230],[-64,1894]]],"type":3,"tags":{"code":"17121","nom":"Couarde-sur-Mer","population":1112,"density":124},"id":"17121"},{"geometry":[[[4160,1924],[4109,2139],[4160,2223],[4160,2548],[3690,2591],[3567,2374],[3652,1945],[4160,1750],[4160,1924]]],"type":3,"tags":{"code":"17142","nom":"Dompierre-sur-Mer","population":6315,"density":342},"id":"17142"},{"geometry":[[[3026,1272],[3463,912],[3712,1204],[3509,1429],[3353,1223],[3026,1272]]],"type":3,"tags":{"code":"17153","nom":"Esnandes","population":2224,"density":289},"id":"17153"},{"geometry":[[[651,2139],[747,1962],[1322,2177],[1426,2407],[626,2540],[651,2139]]],"type":3,"tags":{"code":"17161","nom":"Flotte","population":3150,"density":256},"id":"17161"},{"geometry":[[[3528,3355],[4160,3104],[4160,3296],[4124,3441],[3528,3355]]],"type":3,"tags":{"code":"17193","nom":"Jarne","population":2637,"density":313},"id":"17193"},{"geometry":[[[3261,1958],[3162,2295],[2710,2453],[2795,2027],[3261,1958]]],"type":3,"tags":{"code":"17200","nom":"Lagord","population":7802,"density":973},"id":"17200"},{"geometry":[[[-64,1483],[-46,1483],[-64,1490],[-64,1483]]],"type":3,"tags":{"code":"17207","nom":"Loix","population":745,"density":119},"id":"17207"},{"geometry":[[[4036,-64],[3960,-24],[3940,-64],[4036,-64]]],"type":3,"tags":{"code":"17218","nom":"Marans","population":4476,"density":53},"id":"17218"},{"geometry":[[[2739,1559],[3212,1195],[3438,1257],[3527,1685],[2739,1559]]],"type":3,"tags":{"code":"17222","nom":"Marsilly","population":3176,"density":263},"id":"17222"},{"geometry":[[[2376,1934],[2739,1559],[3340,1949],[2376,1934]]],"type":3,"tags":{"code":"17264","nom":"Nieul-sur-Mer","population":5811,"density":526},"id":"17264"},{"geometry":[[[3439,2824],[3314,2556],[3567,2374],[3690,2591],[4160,2608],[4160,2643],[3891,2704],[3798,3042],[3439,2824]]],"type":3,"tags":{"code":"17274","nom":"Périgny","population":8877,"density":812},"id":"17274"},{"geometry":[[[3261,1958],[3624,2046],[3649,2298],[3376,2487],[3172,2369],[3261,1958]]],"type":3,"tags":{"code":"17291","nom":"Puilboreau","population":6765,"density":852},"id":"17291"},{"geometry":[[[1223,2539],[1426,2407],[1538,2635],[1763,2578],[1476,2912],[1178,2672],[1223,2539]]],"type":3,"tags":{"code":"17297","nom":"Rivedoux-Plage","population":2483,"density":512},"id":"17297"},{"geometry":[[[2995,3091],[2714,3007],[2861,2713],[2313,2874],[1920,2592],[2389,2118],[2715,2267],[2756,2476],[3075,2306],[3376,2487],[3439,2824],[2995,3091]]],"type":3,"tags":{"code":"17300","nom":"Rochelle","population":79851,"density":2527},"id":"17300"},{"geometry":[[[1223,2539],[1178,2672],[1430,2886],[986,2889],[498,2600],[1223,2539]]],"type":3,"tags":{"code":"17360","nom":"Sainte-Marie-de-Ré","population":3412,"density":335},"id":"17360"},{"geometry":[[[73,1954],[747,1962],[574,2141],[73,1954]]],"type":3,"tags":{"code":"17369","nom":"Saint-Martin-de-Ré","population":2355,"density":487},"id":"17369"},{"geometry":[[[4160,1438],[4113,1124],[4160,1146],[4160,1438]]],"type":3,"tags":{"code":"17376","nom":"Saint-Ouen-d'Aunis","population":2150,"density":243},"id":"17376"},{"geometry":[[[3798,3042],[3891,2704],[4160,2693],[4160,2777],[4068,2822],[4013,3055],[4116,3093],[3798,3042]]],"type":3,"tags":{"code":"17391","nom":"Saint-Rogatien","population":2364,"density":459},"id":"17391"},{"geometry":[[[4160,2207],[4109,2139],[4160,1924],[4160,2207]]],"type":3,"tags":{"code":"17407","nom":"Sainte-Soulle","population":5034,"density":228},"id":"17407"},{"geometry":[[[3131,1741],[3527,1685],[3519,1447],[3788,1642],[4139,1503],[4160,1576],[4160,1757],[3624,2046],[3131,1741]]],"type":3,"tags":{"code":"17414","nom":"Saint-Xandre","population":5677,"density":425},"id":"17414"},{"geometry":[[[4160,3776],[3777,3957],[3748,3499],[4124,3441],[4160,3333],[4160,3776]]],"type":3,"tags":{"code":"17420","nom":"Salles-sur-Mer","population":2465,"density":175},"id":"17420"},{"geometry":[[[4156,3814],[4160,3811],[4160,3816],[4156,3814]]],"type":3,"tags":{"code":"17443","nom":"Thairé","population":1897,"density":101},"id":"17443"},{"geometry":[[[3951,901],[4160,950],[4160,1094],[4113,1124],[4104,1502],[3788,1642],[3519,1447],[3712,1204],[3505,921],[3951,901]]],"type":3,"tags":{"code":"17472","nom":"Villedoux","population":2166,"density":139},"id":"17472"},{"geometry":[[[2314,569],[2345,844],[1272,-64],[1507,-64],[1642,266],[2314,569]]],"type":3,"tags":{"code":"85001","nom":"Aiguillon-sur-Mer","population":2845,"density":273},"id":"85001"},{"geometry":[[[3226,106],[3009,0],[3057,-64],[3322,-64],[3226,106]]],"type":3,"tags":{"code":"85185","nom":"Puyravault","population":642,"density":37},"id":"85185"},{"geometry":[[[2378,-64],[2455,272],[2314,569],[1793,358],[1437,-64],[2378,-64]]],"type":3,"tags":{"code":"85255","nom":"Saint-Michel-en-l'Herm","population":2329,"density":40},"id":"85255"},{"geometry":[[[1154,-64],[1324,423],[1561,458],[1275,451],[941,-64],[1154,-64]]],"type":3,"tags":{"code":"85307","nom":"Faute-sur-Mer","population":0,"density":0},"id":"85307"}]}