{"features":[{"geometry":[[[442,-64],[-64,403],[-64,-64],[442,-64]]],"type":3,"tags":{"code":"05027","nom":"Cervières","population":205,"density":2},"id":"05027"},{"geometry":[[[-64,2652],[407,2967],[-64,3051],[-64,2652]]],"type":3,"tags":{"code":"05038","nom":"Château-Ville-Vieille","population":298,"density":4},"id":"05038"},{"geometry":[[[248,393],[531,-64],[3398,-64],[3923,566],[3354,1662],[2355,1698],[1562,2637],[248,393]]],"type":3,"tags":{"code":"05001","nom":"Abriès","population":374,"density":5},"id":"05001"},{"geometry":[[[426,3070],[-64,2694],[-64,469],[248,393],[1562,2637],[1626,3328],[426,3070]]],"type":3,"tags":{"code":"05003","nom":"Aiguilles","population":369,"density":9},"id":"05003"},{"geometry":[[[-64,3100],[316,3053],[1626,3328],[2488,4160],[443,4160],[274,4066],[-64,4138],[-64,3100]]],"type":3,"tags":{"code":"05077","nom":"Molines-en-Queyras","population":307,"density":6},"id":"05077"},{"geometry":[[[1626,3328],[1562,2637],[2017,1998],[3354,1662],[3887,2283],[4065,3629],[4160,3690],[4160,4160],[2505,4160],[1626,3328]]],"type":3,"tags":{"code":"05120","nom":"Ristolas","population":0,"density":0},"id":"05120"},{"geometry":[[[-64,4138],[274,4066],[441,4160],[-64,4160],[-64,4138]]],"type":3,"tags":{"code":"05157","nom":"Saint-Véran","population":160,"density":4},"id":"05157"}]}