{"features":[{"geometry":[[[4160,-64],[4160,3786],[4113,4160],[-64,4160],[-64,-64],[3,-64],[-64,39],[-64,365],[1038,744],[3071,-64],[4160,-64]]],"type":3,"tags":{"code":"49125","nom":"Doué-en-Anjou","population":11029,"density":74},"id":"49125"},{"geometry":[[[3388,-64],[3397,81],[388,674],[-64,407],[-64,39],[3,-64],[3388,-64]]],"type":3,"tags":{"code":"49182","nom":"Louresse-Rochemenier","population":896,"density":35},"id":"49182"},{"geometry":[[[4113,4160],[4160,3786],[4160,4160],[4113,4160]]],"type":3,"tags":{"code":"49364","nom":"Vaudelnay","population":1122,"density":44},"id":"49364"}]}