{"features":[{"geometry":[[[2215,-64],[2319,447],[3064,792],[2590,1839],[1313,593],[803,2068],[-64,1837],[-64,-64],[2215,-64]]],"type":3,"tags":{"code":"17041","nom":"Benon","population":1859,"density":39},"id":"17041"},{"geometry":[[[1060,4160],[1000,848],[1906,662],[4113,2563],[4160,2672],[4160,3796],[3844,4160],[1060,4160]]],"type":3,"tags":{"code":"17338","nom":"Saint-Georges-du-Bois","population":1883,"density":68},"id":"17338"},{"geometry":[[[4160,2983],[2319,447],[2609,-64],[4160,-64],[4160,2983]]],"type":3,"tags":{"code":"17382","nom":"Saint-Pierre-d'Amilly","population":575,"density":29},"id":"17382"},{"geometry":[[[3883,4160],[4160,3880],[4160,4160],[3883,4160]]],"type":3,"tags":{"code":"17394","nom":"Saint-Saturnin-du-Bois","population":915,"density":36},"id":"17394"},{"geometry":[[[-64,4160],[-64,2159],[1289,2300],[1131,4119],[1050,4160],[-64,4160]]],"type":3,"tags":{"code":"17482","nom":"Vouhé","population":674,"density":43},"id":"17482"}]}