{"features":[{"geometry":[[[-64,2888],[511,3953],[440,4160],[-64,4160],[-64,2888]]],"type":3,"tags":{"code":"07166","nom":"Nozières","population":237,"density":11},"id":"07166"},{"geometry":[[[3711,4160],[4107,4101],[4121,4160],[3711,4160]]],"type":3,"tags":{"code":"07073","nom":"Crestet","population":518,"density":52},"id":"07073"},{"geometry":[[[540,2319],[2509,1993],[4160,3214],[4160,4085],[4020,4160],[2715,4160],[2114,2567],[1042,3235],[540,2319]]],"type":3,"tags":{"code":"07014","nom":"Arlebosc","population":380,"density":30},"id":"07014"},{"geometry":[[[2125,2169],[2156,1374],[4160,993],[4160,3162],[2125,2169]]],"type":3,"tags":{"code":"07039","nom":"Bozas","population":255,"density":20},"id":"07039"},{"geometry":[[[1420,-64],[-64,1552],[-64,-64],[1420,-64]]],"type":3,"tags":{"code":"07170","nom":"Pailharès","population":310,"density":16},"id":"07170"},{"geometry":[[[540,2319],[-64,2350],[-64,1652],[1439,-64],[3704,-64],[3087,1296],[1947,1609],[2125,2169],[540,2319]]],"type":3,"tags":{"code":"07236","nom":"Saint-Félicien","population":1119,"density":52},"id":"07236"},{"geometry":[[[4160,898],[3492,895],[3926,-64],[4160,-64],[4160,898]]],"type":3,"tags":{"code":"07301","nom":"Saint-Victor","population":968,"density":30},"id":"07301"},{"geometry":[[[443,4160],[499,3878],[-64,2967],[-64,2511],[540,2319],[1042,3235],[2114,2567],[2717,4160],[443,4160]]],"type":3,"tags":{"code":"07085","nom":"Empurany","population":571,"density":30},"id":"07085"}]}