{"features":[{"geometry":[[[3749,-64],[3695,348],[3050,-64],[3749,-64]]],"type":3,"tags":{"code":"07042","nom":"Bourg-Saint-Andéol","population":7661,"density":179},"id":"07042"},{"geometry":[[[1638,3161],[1232,1813],[2499,1835],[3220,2709],[2400,3176],[3862,2915],[3766,4160],[3664,4160],[3011,3566],[2159,4010],[1638,3161]]],"type":3,"tags":{"code":"07259","nom":"Saint-Just-d'Ardèche","population":1577,"density":152},"id":"07259"},{"geometry":[[[1352,2317],[-64,1593],[-64,-64],[3050,-64],[3695,348],[3862,2915],[2400,3176],[3198,2330],[2293,1769],[1232,1813],[1352,2317]]],"type":3,"tags":{"code":"07264","nom":"Saint-Marcel-d'Ardèche","population":2346,"density":65},"id":"07264"},{"geometry":[[[1336,3114],[-64,2595],[-64,1639],[977,2017],[1336,3114]]],"type":3,"tags":{"code":"07268","nom":"Saint-Martin-d'Ardèche","population":979,"density":173},"id":"07268"},{"geometry":[[[2144,4160],[2159,4010],[3011,3566],[3346,4160],[2144,4160]]],"type":3,"tags":{"code":"30202","nom":"Pont-Saint-Esprit","population":10958,"density":589},"id":"30202"},{"geometry":[[[4160,3232],[3849,3165],[3743,636],[4160,721],[4160,3232]]],"type":3,"tags":{"code":"84064","nom":"Lapalud","population":3853,"density":220},"id":"84064"},{"geometry":[[[4160,827],[3743,636],[3723,-64],[4160,-64],[4160,827]]],"type":3,"tags":{"code":"26235","nom":"Pierrelatte","population":13756,"density":279},"id":"26235"},{"geometry":[[[-64,2371],[196,2708],[-64,2744],[-64,2371]]],"type":3,"tags":{"code":"30005","nom":"Aiguèze","population":212,"density":11},"id":"30005"},{"geometry":[[[-64,2744],[218,2521],[1638,3161],[560,4160],[-64,4160],[-64,2744]]],"type":3,"tags":{"code":"30273","nom":"Saint-Julien-de-Peyrolas","population":1531,"density":122},"id":"30273"},{"geometry":[[[797,4160],[1953,3480],[1917,4160],[797,4160]]],"type":3,"tags":{"code":"30290","nom":"Saint-Paulet-de-Caisson","population":1887,"density":112},"id":"30290"},{"geometry":[[[3817,4160],[3849,3165],[4160,3232],[4160,4160],[3817,4160]]],"type":3,"tags":{"code":"84063","nom":"Lamotte-du-Rhône","population":403,"density":34},"id":"84063"}]}