{"features":[{"geometry":[[[3854,3128],[4160,2049],[4160,1583],[3704,932],[4160,975],[4160,3259],[3854,3128]]],"type":3,"tags":{"code":"02145","nom":"Caumont","population":547,"density":95},"id":"02145"},{"geometry":[[[2702,1970],[3621,1204],[4160,2236],[4160,2416],[2702,1970]]],"type":3,"tags":{"code":"02207","nom":"Commenchon","population":224,"density":68},"id":"02207"},{"geometry":[[[2702,1970],[1706,2613],[1007,788],[2775,-64],[2816,-64],[2702,1970]]],"type":3,"tags":{"code":"02362","nom":"Guivry","population":238,"density":33},"id":"02362"},{"geometry":[[[569,2007],[1361,1251],[1706,2613],[951,3178],[569,2007]]],"type":3,"tags":{"code":"60052","nom":"Beaugies-sous-Bois","population":104,"density":27},"id":"60052"},{"geometry":[[[813,-64],[604,434],[-64,511],[-64,-64],[813,-64]]],"type":3,"tags":{"code":"60062","nom":"Berlancourt","population":310,"density":44},"id":"60062"},{"geometry":[[[-64,511],[604,434],[747,-64],[1411,-64],[1497,214],[495,2015],[-64,2006],[-64,511]]],"type":3,"tags":{"code":"60291","nom":"Guiscard","population":1749,"density":86},"id":"60291"},{"geometry":[[[2196,-64],[1497,214],[1445,-64],[2196,-64]]],"type":3,"tags":{"code":"60693","nom":"Villeselve","population":379,"density":55},"id":"60693"},{"geometry":[[[4160,-64],[4160,1138],[3103,1305],[2822,-64],[4160,-64]]],"type":3,"tags":{"code":"02754","nom":"Ugny-le-Gay","population":187,"density":32},"id":"02754"},{"geometry":[[[3854,3128],[4160,3401],[4160,3857],[3289,4156],[3854,3128]]],"type":3,"tags":{"code":"02542","nom":"Neuflieux","population":80,"density":42},"id":"02542"},{"geometry":[[[1055,4160],[1008,3874],[1287,4160],[1055,4160]]],"type":3,"tags":{"code":"60410","nom":"Mondescourt","population":247,"density":79},"id":"60410"},{"geometry":[[[3840,4160],[4160,3960],[4160,4160],[3840,4160]]],"type":3,"tags":{"code":"02001","nom":"Abbécourt","population":518,"density":87},"id":"02001"},{"geometry":[[[3470,3813],[1893,2521],[3496,2241],[3854,3128],[3470,3813]]],"type":3,"tags":{"code":"02081","nom":"Béthancourt-en-Vaux","population":421,"density":97},"id":"02081"},{"geometry":[[[1648,4160],[811,3244],[1893,2521],[3511,3851],[3031,4160],[1648,4160]]],"type":3,"tags":{"code":"02139","nom":"Caillouël-Crépigny","population":459,"density":68},"id":"02139"},{"geometry":[[[-64,3174],[476,2895],[1215,4160],[-64,4160],[-64,3174]]],"type":3,"tags":{"code":"60287","nom":"Grandrû","population":371,"density":49},"id":"60287"},{"geometry":[[[-64,1786],[473,1895],[951,3178],[-64,3288],[-64,1786]]],"type":3,"tags":{"code":"60389","nom":"Maucourt","population":221,"density":70},"id":"60389"}]}