{"features":[{"geometry":[[[3440,-64],[3506,218],[2909,344],[2429,-64],[3440,-64]]],"type":3,"tags":{"code":"88116","nom":"Cornimont","population":3027,"density":75},"id":"88116"},{"geometry":[[[1367,-64],[447,802],[-64,467],[-64,-64],[1367,-64]]],"type":3,"tags":{"code":"88447","nom":"Saulxures-sur-Moselotte","population":2566,"density":81},"id":"88447"},{"geometry":[[[4160,669],[3506,218],[3483,-64],[4160,-64],[4160,669]]],"type":3,"tags":{"code":"88500","nom":"Ventron","population":805,"density":33},"id":"88500"},{"geometry":[[[3579,2278],[4160,1769],[4160,4112],[2529,3948],[3579,2278]]],"type":3,"tags":{"code":"88081","nom":"Bussang","population":1261,"density":46},"id":"88081"},{"geometry":[[[301,4160],[157,3634],[3523,2111],[2360,4160],[301,4160]]],"type":3,"tags":{"code":"88188","nom":"Fresse-sur-Moselle","population":1662,"density":90},"id":"88188"},{"geometry":[[[260,1195],[1682,-64],[2643,-64],[4160,763],[4160,1734],[3579,2278],[456,2418],[260,1195]]],"type":3,"tags":{"code":"88302","nom":"Ménil","population":970,"density":48},"id":"88302"},{"geometry":[[[-64,619],[447,802],[-64,1835],[-64,619]]],"type":3,"tags":{"code":"88369","nom":"Ramonchamp","population":1815,"density":117},"id":"88369"},{"geometry":[[[2400,4160],[2529,3948],[3161,4160],[2400,4160]]],"type":3,"tags":{"code":"88426","nom":"Saint-Maurice-sur-Moselle","population":1306,"density":36},"id":"88426"},{"geometry":[[[-64,1465],[57,1187],[456,2418],[2347,2203],[157,3634],[326,4160],[-64,4160],[-64,1465]]],"type":3,"tags":{"code":"88468","nom":"Thillot","population":3167,"density":209},"id":"88468"}]}