{"features":[{"geometry":[[[-64,2898],[-55,2926],[-64,2933],[-64,2898]]],"type":3,"tags":{"code":"59279","nom":"Halluin","population":20715,"density":1657},"id":"59279"},{"geometry":[[[-64,2784],[-57,2777],[472,3633],[-64,3824],[-64,2784]]],"type":3,"tags":{"code":"59426","nom":"Neuville-en-Ferrain","population":10002,"density":1615},"id":"59426"},{"geometry":[[[-64,3889],[472,3633],[621,4160],[-64,4160],[-64,3889]]],"type":3,"tags":{"code":"59599","nom":"Tourcoing","population":98772,"density":6542},"id":"59599"},{"geometry":[[[713,4160],[752,4074],[730,4160],[713,4160]]],"type":3,"tags":{"code":"59650","nom":"Wattrelos","population":40847,"density":3034},"id":"59650"}]}