{"features":[{"geometry":[[[3966,-64],[3937,58],[3702,-64],[3966,-64]]],"type":3,"tags":{"code":"77181","nom":"Ferrières-en-Brie","population":3932,"density":642},"id":"77181"},{"geometry":[[[3196,-64],[3937,58],[4160,642],[4160,2004],[3593,2222],[2059,844],[2460,445],[2172,-64],[3196,-64]]],"type":3,"tags":{"code":"77374","nom":"Pontcarré","population":2136,"density":223},"id":"77374"},{"geometry":[[[-64,4027],[211,3686],[1626,4133],[1614,4160],[-64,4160],[-64,4027]]],"type":3,"tags":{"code":"77180","nom":"Férolles-Attilly","population":1248,"density":98},"id":"77180"},{"geometry":[[[3133,4125],[3399,2348],[4160,2003],[4160,4160],[3142,4160],[3133,4125]]],"type":3,"tags":{"code":"77215","nom":"Gretz-Armainvilliers","population":8825,"density":653},"id":"77215"},{"geometry":[[[-64,2734],[671,3474],[22,4160],[-64,4160],[-64,2734]]],"type":3,"tags":{"code":"77249","nom":"Lésigny","population":6923,"density":694},"id":"77249"},{"geometry":[[[193,2690],[1644,2226],[1351,1753],[3510,1738],[3610,3303],[2204,4160],[836,4160],[625,4087],[193,2690]]],"type":3,"tags":{"code":"77350","nom":"Ozoir-la-Ferrière","population":21238,"density":1359},"id":"77350"},{"geometry":[[[3937,58],[3953,-64],[4160,-64],[4160,492],[3937,58]]],"type":3,"tags":{"code":"77058","nom":"Bussy-Saint-Georges","population":27498,"density":1809},"id":"77058"},{"geometry":[[[2727,4160],[2976,4029],[3326,4160],[2727,4160]]],"type":3,"tags":{"code":"77114","nom":"Chevry-Cossigny","population":4075,"density":245},"id":"77114"},{"geometry":[[[2208,-64],[2460,445],[-64,193],[-64,-64],[2208,-64]]],"type":3,"tags":{"code":"77146","nom":"Croissy-Beaubourg","population":2018,"density":187},"id":"77146"},{"geometry":[[[-64,1435],[578,2269],[-64,2657],[-64,1435]]],"type":3,"tags":{"code":"77373","nom":"Pontault-Combault","population":39096,"density":2875},"id":"77373"},{"geometry":[[[578,2269],[-64,1800],[-64,63],[379,-64],[1110,-64],[2693,866],[3204,2081],[578,2269]]],"type":3,"tags":{"code":"77390","nom":"Roissy-en-Brie","population":23229,"density":1698},"id":"77390"}]}