{"features":[{"geometry":[[[182,-64],[-64,276],[-64,-64],[182,-64]]],"type":3,"tags":{"code":"78168","nom":"Coignières","population":4321,"density":536},"id":"78168"},{"geometry":[[[4160,604],[2708,98],[2853,-64],[4160,-64],[4160,604]]],"type":3,"tags":{"code":"78356","nom":"Magny-les-Hameaux","population":9386,"density":563},"id":"78356"},{"geometry":[[[2803,-64],[2708,98],[2376,-64],[2803,-64]]],"type":3,"tags":{"code":"78621","nom":"Trappes","population":34689,"density":2543},"id":"78621"},{"geometry":[[[1151,-64],[933,184],[212,-64],[1151,-64]]],"type":3,"tags":{"code":"78644","nom":"Verrière","population":5994,"density":2832},"id":"78644"},{"geometry":[[[1768,1978],[2920,1605],[4160,3241],[4160,3377],[3039,3484],[1768,1978]]],"type":3,"tags":{"code":"78548","nom":"Saint-Forget","population":436,"density":73},"id":"78548"},{"geometry":[[[4160,3671],[3213,2045],[4160,2030],[4160,3671]]],"type":3,"tags":{"code":"78160","nom":"Chevreuse","population":5502,"density":406},"id":"78160"},{"geometry":[[[3318,4160],[4160,3895],[4160,4160],[3318,4160]]],"type":3,"tags":{"code":"78162","nom":"Choisel","population":540,"density":60},"id":"78162"},{"geometry":[[[1397,1669],[4005,3735],[3624,4160],[2692,4160],[228,3562],[1397,1669]]],"type":3,"tags":{"code":"78193","nom":"Dampierre-en-Yvelines","population":1008,"density":89},"id":"78193"},{"geometry":[[[-64,2093],[280,2129],[451,3805],[279,4160],[-64,4160],[-64,2093]]],"type":3,"tags":{"code":"78220","nom":"Essarts-le-Roi","population":6831,"density":350},"id":"78220"},{"geometry":[[[-64,514],[-54,511],[1440,1558],[388,2798],[280,2129],[-64,2093],[-64,514]]],"type":3,"tags":{"code":"78334","nom":"Lévis-Saint-Nom","population":1603,"density":191},"id":"78334"},{"geometry":[[[4160,949],[3973,542],[4160,607],[4160,949]]],"type":3,"tags":{"code":"78406","nom":"Milon-la-Chapelle","population":295,"density":96},"id":"78406"},{"geometry":[[[652,4160],[1647,3615],[3037,4160],[652,4160]]],"type":3,"tags":{"code":"78590","nom":"Senlisse","population":511,"density":63},"id":"78590"},{"geometry":[[[1397,1669],[17,268],[1202,65],[1180,-64],[2315,-64],[2708,98],[2567,1409],[1397,1669]]],"type":3,"tags":{"code":"78397","nom":"Mesnil-Saint-Denis","population":7276,"density":806},"id":"78397"},{"geometry":[[[2567,1409],[2842,70],[4160,1180],[4160,1572],[2567,1409]]],"type":3,"tags":{"code":"78561","nom":"Saint-Lambert","population":447,"density":68},"id":"78561"}]}