{"features":[{"geometry":[[[-64,1586],[1353,1651],[-64,3008],[-64,1586]]],"type":3,"tags":{"code":"36083","nom":"Giroux","population":121,"density":5},"id":"36083"},{"geometry":[[[593,-64],[393,1212],[-64,1343],[-64,-64],[593,-64]]],"type":3,"tags":{"code":"36102","nom":"Luçay-le-Libre","population":105,"density":9},"id":"36102"},{"geometry":[[[2846,-64],[2768,419],[1515,1795],[393,1212],[246,-64],[2846,-64]]],"type":3,"tags":{"code":"36205","nom":"Saint-Pierre-de-Jards","population":96,"density":5},"id":"36205"},{"geometry":[[[4160,-64],[4160,178],[3249,401],[3420,-64],[4160,-64]]],"type":3,"tags":{"code":"18064","nom":"Chéry","population":233,"density":17},"id":"18064"},{"geometry":[[[1577,4160],[2633,2596],[4160,2794],[4160,4160],[1577,4160]]],"type":3,"tags":{"code":"36065","nom":"Diou","population":256,"density":15},"id":"36065"},{"geometry":[[[-64,3118],[636,2528],[2208,2875],[1689,4160],[-64,4160],[-64,3118]]],"type":3,"tags":{"code":"36152","nom":"Paudy","population":437,"density":14},"id":"36152"},{"geometry":[[[2208,2875],[636,2528],[2540,860],[2829,-64],[3420,-64],[3249,401],[4160,153],[4160,2885],[2208,2875]]],"type":3,"tags":{"code":"36171","nom":"Reuilly","population":1984,"density":76},"id":"36171"},{"geometry":[[[2029,4160],[2072,4091],[2756,4155],[2757,4160],[2029,4160]]],"type":3,"tags":{"code":"36199","nom":"Sainte-Lizaigne","population":1101,"density":41},"id":"36199"}]}