{"features":[{"geometry":[[[1334,-64],[1320,218],[-64,1194],[-64,-64],[1334,-64]]],"type":3,"tags":{"code":"2B023","nom":"Asco","population":116,"density":1},"id":"2B023"},{"geometry":[[[4160,1865],[2048,2322],[963,389],[1129,-64],[4075,-64],[4160,-10],[4160,1865]]],"type":3,"tags":{"code":"2B081","nom":"Castiglione","population":40,"density":2},"id":"2B081"},{"geometry":[[[1707,4160],[2768,2262],[4160,1964],[4160,4092],[4064,4160],[1707,4160]]],"type":3,"tags":{"code":"2B083","nom":"Castirla","population":166,"density":7},"id":"2B083"},{"geometry":[[[-64,4160],[-64,1262],[963,389],[1847,2201],[2768,2262],[1707,4160],[-64,4160]]],"type":3,"tags":{"code":"2B095","nom":"Corscia","population":123,"density":2},"id":"2B095"},{"geometry":[[[4160,1],[3911,-64],[4160,-64],[4160,1]]],"type":3,"tags":{"code":"2B244","nom":"Popolasca","population":41,"density":4},"id":"2B244"},{"geometry":[[[4086,4160],[4160,4087],[4160,4160],[4086,4160]]],"type":3,"tags":{"code":"2B289","nom":"Soveria","population":109,"density":9},"id":"2B289"}]}