{"features":[{"geometry":[[[2707,-64],[1956,580],[1246,142],[1261,-64],[2707,-64]]],"type":3,"tags":{"code":"30152","nom":"Mages","population":2106,"density":166},"id":"30152"},{"geometry":[[[3498,4160],[3741,3697],[4160,3791],[4160,4160],[3498,4160]]],"type":3,"tags":{"code":"30197","nom":"Plans","population":292,"density":47},"id":"30197"},{"geometry":[[[1052,-64],[1956,580],[3934,880],[3275,2387],[962,2337],[-64,3080],[-64,-64],[1052,-64]]],"type":3,"tags":{"code":"30223","nom":"Rousson","population":4456,"density":135},"id":"30223"},{"geometry":[[[4028,-64],[4091,910],[2642,200],[2622,-64],[4028,-64]]],"type":3,"tags":{"code":"30271","nom":"Saint-Julien-de-Cassagnas","population":734,"density":161},"id":"30271"},{"geometry":[[[-64,4160],[-64,3194],[454,3419],[863,4160],[-64,4160]]],"type":3,"tags":{"code":"30294","nom":"Saint-Privat-des-Vieux","population":5703,"density":362},"id":"30294"},{"geometry":[[[3125,2452],[1772,4160],[845,4160],[-64,3382],[-64,3080],[962,2337],[3125,2452]]],"type":3,"tags":{"code":"30305","nom":"Salindres","population":3648,"density":315},"id":"30305"},{"geometry":[[[3651,2538],[4050,3701],[3717,4160],[1628,4160],[2764,2604],[3651,2538]]],"type":3,"tags":{"code":"30318","nom":"Servas","population":219,"density":20},"id":"30318"},{"geometry":[[[4160,238],[4110,283],[3845,-64],[4160,-64],[4160,238]]],"type":3,"tags":{"code":"30204","nom":"Potelières","population":363,"density":56},"id":"30204"},{"geometry":[[[4160,2036],[3292,2204],[4110,283],[4160,250],[4160,2036]]],"type":3,"tags":{"code":"30008","nom":"Allègre-les-Fumades","population":1002,"density":40},"id":"30008"},{"geometry":[[[4160,3471],[3651,2538],[4160,2420],[4160,3471]]],"type":3,"tags":{"code":"30187","nom":"Navacelles","population":317,"density":28},"id":"30187"}]}