{"features":[{"geometry":[[[240,4160],[-64,3488],[-64,2011],[226,1937],[1454,3228],[599,4160],[240,4160]]],"type":3,"tags":{"code":"77140","nom":"Coutençon","population":260,"density":42},"id":"77140"},{"geometry":[[[147,779],[-64,780],[-64,-64],[2387,-64],[1504,814],[147,779]]],"type":3,"tags":{"code":"77190","nom":"Fontains","population":256,"density":18},"id":"77190"},{"geometry":[[[3462,2400],[3355,88],[4160,510],[4160,3321],[3462,2400]]],"type":3,"tags":{"code":"77223","nom":"Gurcy-le-Châtel","population":559,"density":44},"id":"77223"},{"geometry":[[[-64,3494],[245,4160],[-64,4160],[-64,3494]]],"type":3,"tags":{"code":"77245","nom":"Laval-en-Brie","population":412,"density":20},"id":"77245"},{"geometry":[[[4160,592],[3225,147],[3722,-64],[4160,-64],[4160,592]]],"type":3,"tags":{"code":"77286","nom":"Meigneux","population":236,"density":30},"id":"77286"},{"geometry":[[[1206,4160],[1000,3490],[3462,2400],[4142,3719],[4160,3723],[4160,4160],[1206,4160]]],"type":3,"tags":{"code":"77311","nom":"Montigny-Lencoup","population":1358,"density":66},"id":"77311"},{"geometry":[[[860,4160],[1188,3988],[1237,4160],[860,4160]]],"type":3,"tags":{"code":"77439","nom":"Salins","population":1165,"density":110},"id":"77439"},{"geometry":[[[226,1937],[147,779],[1504,814],[2141,-64],[2763,-64],[3728,1037],[3117,1468],[3462,2400],[1932,3587],[226,1937]]],"type":3,"tags":{"code":"77509","nom":"Villeneuve-les-Bordes","population":610,"density":29},"id":"77509"},{"geometry":[[[226,1937],[-64,1937],[-64,1191],[226,1937]]],"type":3,"tags":{"code":"77089","nom":"Chapelle-Rablais","population":913,"density":59},"id":"77089"}]}