{"features":[{"geometry":[[[1370,1380],[1657,1426],[1816,1839],[1158,2259],[1060,2007],[1356,1783],[1370,1380]]],"type":3,"tags":{"code":"57635","nom":"Schalbach","population":372,"density":30},"id":"57635"},{"geometry":[[[1935,133],[1864,-64],[2513,-64],[2440,-40],[2280,306],[1935,133]]],"type":3,"tags":{"code":"67514","nom":"Waldhambach","population":598,"density":47},"id":"67514"},{"geometry":[[[1904,1197],[1701,794],[1879,686],[2118,1224],[1904,1197]]],"type":3,"tags":{"code":"67105","nom":"Drulingen","population":1397,"density":309},"id":"67105"},{"geometry":[[[2364,3262],[2233,3210],[2330,3022],[2571,3148],[2506,3348],[2364,3262]]],"type":3,"tags":{"code":"57169","nom":"Dannelbourg","population":505,"density":172},"id":"57169"},{"geometry":[[[2352,3458],[2243,3609],[1810,3475],[2058,3088],[2364,3262],[2352,3458]]],"type":3,"tags":{"code":"57315","nom":"Henridorff","population":706,"density":96},"id":"57315"},{"geometry":[[[1258,3479],[983,3407],[1166,2936],[1693,3315],[1258,3479]]],"type":3,"tags":{"code":"57333","nom":"Hommarting","population":847,"density":83},"id":"57333"},{"geometry":[[[2895,3344],[2720,3928],[2491,3689],[2895,3344]]],"type":3,"tags":{"code":"57339","nom":"Hultehouse","population":360,"density":79},"id":"57339"},{"geometry":[[[2525,3523],[2318,3437],[2364,3262],[2506,3348],[2791,3070],[2930,3249],[2525,3523]]],"type":3,"tags":{"code":"57427","nom":"Lutzelbourg","population":551,"density":95},"id":"57427"},{"geometry":[[[1016,2713],[873,2331],[1113,2149],[1300,2745],[1122,2876],[1016,2713]]],"type":3,"tags":{"code":"57713","nom":"Vieux-Lixheim","population":249,"density":38},"id":"57713"},{"geometry":[[[2058,3088],[1904,3199],[1777,2974],[2058,3088]]],"type":3,"tags":{"code":"57743","nom":"Waltembourg","population":227,"density":171},"id":"57743"},{"geometry":[[[1786,2123],[2031,2133],[1932,2540],[1719,2410],[1786,2123]]],"type":3,"tags":{"code":"57747","nom":"Wintersbourg","population":262,"density":65},"id":"57747"},{"geometry":[[[1267,784],[1221,1158],[877,991],[917,687],[1267,784]]],"type":3,"tags":{"code":"67136","nom":"Eywiller","population":274,"density":56},"id":"67136"},{"geometry":[[[801,1344],[945,1160],[1289,1304],[1356,1783],[894,1784],[801,1344]]],"type":3,"tags":{"code":"67201","nom":"Hirschland","population":303,"density":28},"id":"67201"},{"geometry":[[[894,1784],[1265,1860],[854,2232],[675,1927],[894,1784]]],"type":3,"tags":{"code":"67386","nom":"Rauwiller","population":232,"density":47},"id":"67386"},{"geometry":[[[2909,-64],[2828,156],[2272,296],[2440,-40],[2610,-64],[2909,-64]]],"type":3,"tags":{"code":"67522","nom":"Weislingen","population":525,"density":76},"id":"67522"},{"geometry":[[[2821,3082],[2959,2967],[2856,2628],[2967,2442],[3287,2749],[2978,3383],[2821,3082]]],"type":3,"tags":{"code":"57168","nom":"Danne-et-Quatre-Vents","population":670,"density":94},"id":"57168"},{"geometry":[[[1869,420],[1753,125],[2217,290],[1869,420]]],"type":3,"tags":{"code":"67002","nom":"Adamswiller","population":407,"density":121},"id":"67002"},{"geometry":[[[1786,2760],[1834,2530],[2155,2673],[1928,2902],[1786,2760]]],"type":3,"tags":{"code":"57100","nom":"Bourscheid","population":173,"density":42},"id":"57100"},{"geometry":[[[1187,2881],[1467,2521],[1755,2695],[1700,3084],[1904,3199],[1698,3404],[1525,3053],[1187,2881]]],"type":3,"tags":{"code":"57114","nom":"Brouviller","population":412,"density":41},"id":"57114"},{"geometry":[[[1388,3918],[1926,4113],[1542,4160],[927,4160],[959,4009],[1388,3918]]],"type":3,"tags":{"code":"57544","nom":"Plaine-de-Walsch","population":601,"density":125},"id":"57544"},{"geometry":[[[2447,812],[1975,952],[2210,540],[2545,524],[2447,812]]],"type":3,"tags":{"code":"67013","nom":"Asswiller","population":268,"density":45},"id":"67013"},{"geometry":[[[3287,2749],[3029,2276],[3608,2210],[3439,2492],[4009,2829],[3287,2749]]],"type":3,"tags":{"code":"67117","nom":"Eckartswiller","population":420,"density":34},"id":"67117"},{"geometry":[[[4160,2622],[3641,2409],[3652,2199],[4160,2091],[4160,2622]]],"type":3,"tags":{"code":"67129","nom":"Ernolsheim-lès-Saverne","population":601,"density":55},"id":"67129"},{"geometry":[[[3705,3536],[3911,3586],[3842,3806],[3705,3536]]],"type":3,"tags":{"code":"67161","nom":"Gottenhouse","population":366,"density":280},"id":"67161"},{"geometry":[[[3375,4160],[3356,3896],[2923,3873],[2862,4160],[2507,4160],[2458,4076],[2667,4037],[2970,3380],[3723,3538],[3826,3801],[3523,3844],[3400,4160],[3375,4160]]],"type":3,"tags":{"code":"67179","nom":"Haegen","population":671,"density":33},"id":"67179"},{"geometry":[[[3564,4160],[3850,3657],[4160,3667],[4160,4160],[3564,4160]]],"type":3,"tags":{"code":"67283","nom":"Marmoutier","population":2699,"density":191},"id":"67283"},{"geometry":[[[3989,2787],[4139,2731],[4160,2772],[4160,3181],[4070,3168],[3870,2930],[3989,2787]]],"type":3,"tags":{"code":"67302","nom":"Monswiller","population":1995,"density":418},"id":"67302"},{"geometry":[[[3362,2779],[3864,2933],[3587,3046],[3362,2779]]],"type":3,"tags":{"code":"67366","nom":"Ottersthal","population":805,"density":263},"id":"67366"},{"geometry":[[[4160,3673],[4143,3719],[3847,3519],[4160,3473],[4160,3673]]],"type":3,"tags":{"code":"67367","nom":"Otterswiller","population":1309,"density":400},"id":"67367"},{"geometry":[[[2588,994],[2356,1282],[2067,1066],[2365,809],[2588,994]]],"type":3,"tags":{"code":"67369","nom":"Ottwiller","population":246,"density":48},"id":"67369"},{"geometry":[[[2870,4160],[2923,3873],[3356,3896],[3375,4160],[2870,4160]]],"type":3,"tags":{"code":"67391","nom":"Reinhardsmunster","population":430,"density":23},"id":"67391"},{"geometry":[[[3608,2210],[3689,2453],[4160,2715],[4160,2721],[3439,2492],[3608,2210]]],"type":3,"tags":{"code":"67425","nom":"Saint-Jean-Saverne","population":542,"density":83},"id":"67425"},{"geometry":[[[4160,3470],[3270,3572],[2978,3383],[3287,2749],[3587,3046],[3983,2951],[4160,3249],[4160,3470]]],"type":3,"tags":{"code":"67437","nom":"Saverne","population":11460,"density":435},"id":"67437"},{"geometry":[[[4160,3653],[4155,3646],[4160,3635],[4160,3653]]],"type":3,"tags":{"code":"67459","nom":"Schwenheim","population":742,"density":148},"id":"67459"},{"geometry":[[[1797,1279],[2356,1282],[2074,1393],[2199,1832],[1827,1559],[1918,1455],[1797,1279]]],"type":3,"tags":{"code":"67467","nom":"Siewiller","population":380,"density":62},"id":"67467"},{"geometry":[[[4160,2891],[4151,2877],[4160,2868],[4160,2891]]],"type":3,"tags":{"code":"67478","nom":"Steinbourg","population":1897,"density":151},"id":"67478"},{"geometry":[[[3842,3806],[3441,4160],[3400,4160],[3523,3844],[3842,3806]]],"type":3,"tags":{"code":"67489","nom":"Thal-Marmoutier","population":826,"density":240},"id":"67489"},{"geometry":[[[1732,1983],[1727,2165],[1499,2138],[1579,1885],[1732,1983]]],"type":3,"tags":{"code":"57080","nom":"Bickenholtz","population":86,"density":34},"id":"57080"},{"geometry":[[[1094,327],[1562,207],[1616,406],[1516,672],[1108,805],[976,678],[1167,537],[1094,327]]],"type":3,"tags":{"code":"67029","nom":"Berg","population":347,"density":45},"id":"67029"},{"geometry":[[[1869,420],[1562,207],[1753,125],[1869,420]]],"type":3,"tags":{"code":"67396","nom":"Rexingen","population":202,"density":87},"id":"67396"},{"geometry":[[[1869,420],[2381,559],[1973,792],[1869,420]]],"type":3,"tags":{"code":"67111","nom":"Durstel","population":418,"density":88},"id":"67111"},{"geometry":[[[3310,-64],[3029,-6],[3017,-64],[3310,-64]]],"type":3,"tags":{"code":"67509","nom":"Volksberg","population":353,"density":37},"id":"67509"},{"geometry":[[[1484,2043],[1770,2062],[1719,2410],[1378,2477],[1484,2043]]],"type":3,"tags":{"code":"57216","nom":"Fleisheim","population":135,"density":33},"id":"57216"},{"geometry":[[[1657,1426],[1797,1279],[2006,1692],[1809,2114],[1657,1426]]],"type":3,"tags":{"code":"57703","nom":"Veckersviller","population":230,"density":47},"id":"57703"},{"geometry":[[[1701,794],[1506,694],[1590,372],[1821,567],[1701,794]]],"type":3,"tags":{"code":"67036","nom":"Bettwiller","population":299,"density":71},"id":"67036"},{"geometry":[[[2547,1567],[2654,1735],[2496,1872],[2074,1393],[2334,1461],[2425,1284],[2547,1567]]],"type":3,"tags":{"code":"67071","nom":"Bust","population":454,"density":67},"id":"67071"},{"geometry":[[[2258,2122],[2493,1992],[2675,2213],[2423,2365],[2258,2122]]],"type":3,"tags":{"code":"57064","nom":"Berling","population":313,"density":101},"id":"57064"},{"geometry":[[[2199,1832],[2228,1645],[2699,1840],[2188,2131],[2199,1832]]],"type":3,"tags":{"code":"57291","nom":"Hangviller","population":253,"density":56},"id":"57291"},{"geometry":[[[1719,2410],[1834,2530],[1704,2720],[1484,2635],[1719,2410]]],"type":3,"tags":{"code":"57317","nom":"Hérange","population":104,"density":37},"id":"57317"},{"geometry":[[[1178,2244],[1484,2043],[1335,2282],[1473,2520],[1300,2745],[1178,2244]]],"type":3,"tags":{"code":"57407","nom":"Lixheim","population":552,"density":134},"id":"57407"},{"geometry":[[[2188,2131],[1919,2177],[1821,1990],[2072,1682],[2188,2131]]],"type":3,"tags":{"code":"57462","nom":"Metting","population":410,"density":79},"id":"57462"},{"geometry":[[[2233,3210],[2071,3095],[2128,2630],[2375,2372],[2469,2958],[2233,3210]]],"type":3,"tags":{"code":"57468","nom":"Mittelbronn","population":636,"density":82},"id":"57468"},{"geometry":[[[2428,2998],[2430,2551],[3029,2276],[2856,2628],[2936,3026],[2578,3208],[2428,2998]]],"type":3,"tags":{"code":"57540","nom":"Phalsbourg","population":4688,"density":356},"id":"57540"},{"geometry":[[[2058,3088],[1700,3084],[1730,2762],[2124,2826],[2058,3088]]],"type":3,"tags":{"code":"57614","nom":"Saint-Jean-Kourtzerode","population":647,"density":233},"id":"57614"},{"geometry":[[[2188,2131],[2423,2365],[2231,2402],[2188,2131]]],"type":3,"tags":{"code":"57709","nom":"Vescheim","population":305,"density":162},"id":"57709"},{"geometry":[[[2783,2125],[3029,2276],[2541,2593],[2375,2372],[2783,2125]]],"type":3,"tags":{"code":"57721","nom":"Vilsberg","population":348,"density":70},"id":"57721"},{"geometry":[[[1932,2540],[2084,2151],[2239,2411],[2128,2630],[1932,2540]]],"type":3,"tags":{"code":"57761","nom":"Zilling","population":279,"density":78},"id":"57761"},{"geometry":[[[1258,3479],[1821,3419],[1647,3769],[1350,3719],[1258,3479]]],"type":3,"tags":{"code":"57033","nom":"Arzviller","population":516,"density":101},"id":"57033"},{"geometry":[[[2136,3835],[2484,3428],[2491,3689],[2720,3928],[2399,4078],[2136,3835]]],"type":3,"tags":{"code":"57244","nom":"Garrebourg","population":485,"density":58},"id":"57244"},{"geometry":[[[1388,3918],[1128,3571],[1258,3479],[1350,3719],[1998,4048],[1388,3918]]],"type":3,"tags":{"code":"57280","nom":"Guntzviller","population":353,"density":65},"id":"57280"},{"geometry":[[[1388,3918],[1182,4077],[607,3684],[983,3407],[1388,3918]]],"type":3,"tags":{"code":"57505","nom":"Niderviller","population":1138,"density":104},"id":"57505"},{"geometry":[[[1647,3769],[1644,3546],[1789,3495],[2243,3609],[1998,4048],[1647,3769]]],"type":3,"tags":{"code":"57618","nom":"Saint-Louis","population":617,"density":68},"id":"57618"},{"geometry":[[[1516,672],[1565,837],[1236,865],[1516,672]]],"type":3,"tags":{"code":"67178","nom":"Gungwiller","population":284,"density":169},"id":"67178"},{"geometry":[[[1269,-51],[1273,-64],[1778,-64],[1935,133],[1562,207],[1269,-51]]],"type":3,"tags":{"code":"67278","nom":"Mackwiller","population":525,"density":57},"id":"67278"},{"geometry":[[[1269,-51],[1562,207],[1094,327],[1031,33],[1269,-51]]],"type":3,"tags":{"code":"67488","nom":"Thal-Drulingen","population":186,"density":35},"id":"67488"},{"geometry":[[[1701,794],[1929,1139],[1692,1424],[1150,1283],[1317,896],[1701,794]]],"type":3,"tags":{"code":"67528","nom":"Weyer","population":509,"density":43},"id":"67528"},{"geometry":[[[4160,2092],[3678,2172],[3555,1839],[3757,1397],[4056,1498],[4076,2108],[4160,2032],[4160,2092]]],"type":3,"tags":{"code":"67103","nom":"Dossenheim-sur-Zinsel","population":1059,"density":61},"id":"67103"},{"geometry":[[[3936,434],[4111,291],[4160,339],[4160,485],[3939,519],[4103,683],[4086,953],[3322,951],[3435,584],[3936,434]]],"type":3,"tags":{"code":"67126","nom":"Erckartswiller","population":285,"density":27},"id":"67126"},{"geometry":[[[2699,1840],[2887,1799],[2857,1399],[3084,1189],[3296,1400],[3175,1692],[3245,2195],[2881,2201],[2699,1840]]],"type":3,"tags":{"code":"67133","nom":"Eschbourg","population":455,"density":32},"id":"67133"},{"geometry":[[[3017,119],[2935,356],[2738,326],[3017,119]]],"type":3,"tags":{"code":"67148","nom":"Frohmuhl","population":156,"density":95},"id":"67148"},{"geometry":[[[3017,119],[3304,517],[3005,513],[3017,119]]],"type":3,"tags":{"code":"67198","nom":"Hinsbourg","population":122,"density":36},"id":"67198"},{"geometry":[[[2547,1567],[2474,1315],[2267,1378],[2440,1264],[2459,993],[3130,1075],[3050,1349],[2740,1283],[2547,1567]]],"type":3,"tags":{"code":"67273","nom":"Lohr","population":444,"density":43},"id":"67273"},{"geometry":[[[3608,2210],[3164,2060],[3293,1433],[4160,1295],[4160,2059],[4076,2108],[4056,1498],[3757,1397],[3555,1839],[3701,2184],[3608,2210]]],"type":3,"tags":{"code":"67322","nom":"Neuwiller-lès-Saverne","population":1079,"density":34},"id":"67322"},{"geometry":[[[2588,994],[2448,856],[2558,608],[2978,547],[3114,733],[3060,1026],[2588,994]]],"type":3,"tags":{"code":"67370","nom":"Petersbach","population":664,"density":74},"id":"67370"},{"geometry":[[[2978,547],[3435,584],[3340,985],[4086,953],[3946,1070],[4007,1258],[3293,1433],[3084,1189],[3114,733],[2978,547]]],"type":3,"tags":{"code":"67371","nom":"Petite-Pierre","population":586,"density":30},"id":"67371"},{"geometry":[[[2783,2125],[2493,1992],[2699,1840],[2783,2125]]],"type":3,"tags":{"code":"67373","nom":"Pfalzweyer","population":329,"density":147},"id":"67373"},{"geometry":[[[2982,21],[3441,66],[3281,436],[2982,21]]],"type":3,"tags":{"code":"67381","nom":"Puberg","population":319,"density":65},"id":"67381"},{"geometry":[[[3415,161],[3392,-64],[3769,-64],[3415,161]]],"type":3,"tags":{"code":"67413","nom":"Rosteig","population":464,"density":60},"id":"67413"},{"geometry":[[[2547,1567],[2762,1281],[2887,1799],[2699,1840],[2547,1567]]],"type":3,"tags":{"code":"67454","nom":"Schœnbourg","population":366,"density":72},"id":"67454"},{"geometry":[[[4086,953],[3973,486],[4160,527],[4160,1143],[3998,1243],[3946,1070],[4086,953]]],"type":3,"tags":{"code":"67475","nom":"Sparsbach","population":238,"density":17},"id":"67475"},{"geometry":[[[2558,608],[2532,398],[2757,287],[3009,489],[2558,608]]],"type":3,"tags":{"code":"67483","nom":"Struth","population":213,"density":51},"id":"67483"},{"geometry":[[[2192,413],[2802,161],[2545,524],[2192,413]]],"type":3,"tags":{"code":"67491","nom":"Tieffenbach","population":243,"density":48},"id":"67491"},{"geometry":[[[4007,1258],[4160,1154],[4160,1316],[4007,1258]]],"type":3,"tags":{"code":"67524","nom":"Weiterswiller","population":515,"density":65},"id":"67524"},{"geometry":[[[4160,313],[4145,295],[4160,287],[4160,-64],[4160,-64],[4160,313]]],"type":3,"tags":{"code":"67535","nom":"Wimmenau","population":1070,"density":51},"id":"67535"},{"geometry":[[[3648,136],[3693,-64],[4160,-64],[4160,307],[3936,434],[3648,136]]],"type":3,"tags":{"code":"67538","nom":"Wingen-sur-Moder","population":1530,"density":89},"id":"67538"},{"geometry":[[[3304,517],[3415,161],[3936,434],[3304,517]]],"type":3,"tags":{"code":"67559","nom":"Zittersheim","population":232,"density":30},"id":"67559"},{"geometry":[[[-64,2517],[72,2487],[85,2887],[-64,2976],[-64,2517]]],"type":3,"tags":{"code":"57180","nom":"Dolving","population":344,"density":52},"id":"57180"},{"geometry":[[[861,742],[726,399],[961,121],[1167,537],[861,742]]],"type":3,"tags":{"code":"67070","nom":"Burbach","population":280,"density":44},"id":"67070"},{"geometry":[[[209,2097],[-64,2203],[-64,1802],[185,1804],[209,2097]]],"type":3,"tags":{"code":"57071","nom":"Bettborn","population":406,"density":62},"id":"57071"},{"geometry":[[[157,3792],[593,3222],[905,3432],[506,3802],[509,4152],[157,3792]]],"type":3,"tags":{"code":"57119","nom":"Buhl-Lorraine","population":1204,"density":104},"id":"57119"},{"geometry":[[[-64,3496],[69,3841],[-64,3955],[-64,3496]]],"type":3,"tags":{"code":"57344","nom":"Imling","population":685,"density":105},"id":"57344"},{"geometry":[[[-64,748],[199,866],[267,1273],[-64,1081],[-64,748]]],"type":3,"tags":{"code":"57506","nom":"Niederstinzel","population":235,"density":18},"id":"57506"},{"geometry":[[[242,1340],[225,1126],[487,1053],[797,1194],[242,1340]]],"type":3,"tags":{"code":"57551","nom":"Postroff","population":196,"density":39},"id":"57551"},{"geometry":[[[344,-64],[223,-16],[226,-64],[344,-64]]],"type":3,"tags":{"code":"67434","nom":"Sarre-Union","population":2731,"density":177},"id":"67434"},{"geometry":[[[-64,1133],[244,1298],[263,1533],[-64,1533],[-64,1133]]],"type":3,"tags":{"code":"57210","nom":"Fénétrange","population":639,"density":43},"id":"57210"},{"geometry":[[[-64,2950],[31,2861],[55,3086],[-64,3112],[-64,2950]]],"type":3,"tags":{"code":"57304","nom":"Haut-Clocher","population":340,"density":29},"id":"57304"},{"geometry":[[[247,1907],[674,2050],[310,2162],[156,1996],[247,1907]]],"type":3,"tags":{"code":"57310","nom":"Hellering-lès-Fénétrange","population":186,"density":46},"id":"57310"},{"geometry":[[[-64,4005],[307,3818],[555,4160],[-64,4160],[-64,4005]]],"type":3,"tags":{"code":"57321","nom":"Hesse","population":549,"density":42},"id":"57321"},{"geometry":[[[695,2828],[559,2412],[1001,2188],[1043,2331],[867,2376],[998,2751],[695,2828]]],"type":3,"tags":{"code":"57324","nom":"Hilbesheim","population":617,"density":82},"id":"57324"},{"geometry":[[[-64,2281],[419,2179],[72,2487],[-64,2424],[-64,2281]]],"type":3,"tags":{"code":"57518","nom":"Oberstinzel","population":316,"density":62},"id":"57518"},{"geometry":[[[905,3432],[477,2921],[1016,2713],[1187,2881],[1097,3310],[905,3432]]],"type":3,"tags":{"code":"57566","nom":"Réding","population":2280,"density":195},"id":"57566"},{"geometry":[[[-64,1563],[271,1591],[147,1834],[-64,1768],[-64,1563]]],"type":3,"tags":{"code":"57592","nom":"Romelfing","population":328,"density":30},"id":"57592"},{"geometry":[[[85,2887],[72,2487],[419,2179],[703,2769],[85,2887]]],"type":3,"tags":{"code":"57629","nom":"Sarraltroff","population":789,"density":65},"id":"57629"},{"geometry":[[[69,3841],[-64,3614],[-64,3096],[55,3086],[110,2872],[496,2932],[638,3194],[69,3841]]],"type":3,"tags":{"code":"57630","nom":"Sarrebourg","population":12170,"density":734},"id":"57630"},{"geometry":[[[509,4152],[506,3802],[648,3782],[649,4160],[519,4160],[509,4152]]],"type":3,"tags":{"code":"57637","nom":"Schneckenbusch","population":314,"density":146},"id":"57637"},{"geometry":[[[801,1344],[884,1828],[501,1804],[578,1330],[801,1344]]],"type":3,"tags":{"code":"67017","nom":"Baerendorf","population":304,"density":40},"id":"67017"},{"geometry":[[[119,369],[149,601],[359,630],[347,996],[-64,782],[-64,344],[119,369]]],"type":3,"tags":{"code":"67091","nom":"Diedendorf","population":314,"density":30},"id":"67091"},{"geometry":[[[873,959],[1221,1158],[666,1313],[873,959]]],"type":3,"tags":{"code":"67134","nom":"Eschwiller","population":173,"density":48},"id":"67134"},{"geometry":[[[675,1927],[854,2232],[543,2424],[419,2179],[675,1927]]],"type":3,"tags":{"code":"67159","nom":"Gœrlingen","population":210,"density":56},"id":"67159"},{"geometry":[[[119,369],[-64,297],[-64,-64],[211,-64],[119,369]]],"type":3,"tags":{"code":"67183","nom":"Harskirchen","population":895,"density":61},"id":"67183"},{"geometry":[[[247,1907],[242,1340],[578,1330],[445,1697],[651,1948],[247,1907]]],"type":3,"tags":{"code":"67241","nom":"Kirrberg","population":167,"density":26},"id":"67241"},{"geometry":[[[1170,-64],[1002,143],[730,-64],[1170,-64]]],"type":3,"tags":{"code":"67401","nom":"Rimsdorf","population":287,"density":47},"id":"67401"},{"geometry":[[[345,622],[108,553],[223,-16],[337,-64],[726,-64],[961,121],[730,532],[345,622]]],"type":3,"tags":{"code":"67435","nom":"Sarrewerden","population":816,"density":49},"id":"67435"},{"geometry":[[[345,622],[730,532],[922,823],[733,1056],[225,1126],[345,622]]],"type":3,"tags":{"code":"67552","nom":"Wolfskirchen","population":332,"density":31},"id":"67552"},{"geometry":[[[649,4160],[645,3754],[1182,4077],[959,4009],[927,4160],[649,4160]]],"type":3,"tags":{"code":"57113","nom":"Brouderdorff","population":987,"density":206},"id":"57113"},{"geometry":[[[1946,4122],[2136,3835],[2418,4160],[2316,4160],[2295,4143],[2255,4160],[1947,4160],[1946,4122]]],"type":3,"tags":{"code":"57300","nom":"Haselbourg","population":295,"density":48},"id":"57300"}]}